pypaya_pgn_parser/__init__.py
pypaya_pgn_parser/headers.py
pypaya_pgn_parser/movetext_parser.py
pypaya_pgn_parser/movetext_tokenizer.py
pypaya_pgn_parser/pgn_parser.py
pypaya_pgn_parser-0.1.1.dist-info/LICENSE
pypaya_pgn_parser-0.1.1.dist-info/METADATA
pypaya_pgn_parser-0.1.1.dist-info/WHEEL
pypaya_pgn_parser-0.1.1.dist-info/RECORD
