Metadata-Version: 2.1
Name: pypaya-pgn-parser
Version: 0.1.1
Summary: A lightweight Python package that provides efficient parsing capabilities for Portable Game Notation (PGN) chess files
Home-page: https://github.com/PypayaTech/pypaya-pgn-parser
License: MIT
Keywords: chess,pgn,parser
Author: PypayaTech
Requires-Python: >=3.7,<4.0
Classifier: License :: OSI Approved :: MIT License
Classifier: Operating System :: OS Independent
Classifier: Programming Language :: Python :: 3
Classifier: Programming Language :: Python :: 3.7
Classifier: Programming Language :: Python :: 3.8
Classifier: Programming Language :: Python :: 3.9
Classifier: Programming Language :: Python :: 3.10
Classifier: Programming Language :: Python :: 3.11
Classifier: Programming Language :: Python :: 3.12
Requires-Dist: typing-extensions (>=4.0.0,<5.0.0) ; python_version < "3.8"
Project-URL: Repository, https://github.com/PypayaTech/pypaya-pgn-parser
